midas_timesim/__init__.py
midas_timesim/meta.py
midas_timesim/module.py
midas_timesim/simulator.py
midas_timesim-2.1.1.dist-info/licenses/LICENSE
midas_timesim-2.1.1.dist-info/METADATA
midas_timesim-2.1.1.dist-info/WHEEL
midas_timesim-2.1.1.dist-info/top_level.txt
midas_timesim-2.1.1.dist-info/RECORD
