Metadata-Version: 2.4
Name: midas-timesim
Version: 2.1.1
Summary: A midas module for a time simulator.
Author-email: Stephan Balduin <stephan.balduin@offis.de>
Project-URL: Documentation, https://midas-mosaik.gitlab.io/midas
Requires-Python: >=3.10
License-File: LICENSE
Requires-Dist: midas-mosaik>=2.1.0
Requires-Dist: mosaik_api
Requires-Dist: numpy
Dynamic: license-file
